<error errorId="8f11fee3-d57a-474f-bece-e2a986f2e5b2" application="/LM/W3SVC/64/ROOT" host="LT0610QT23201" type="System.Web.HttpException" message="The controller for path '/Error.cshtml' was not found or does not implement IController." source="System.Web.Mvc" detail="System.Web.HttpException (0x80004005): The controller for path '/Error.cshtml' was not found or does not implement IController.&#xD;&#xA;   at System.Web.Mvc.DefaultControllerFactory.GetControllerInstance(RequestContext requestContext, Type controllerType)&#xD;&#xA;   at System.Web.Mvc.DefaultControllerFactory.CreateController(RequestContext requestContext, String controllerName)&#xD;&#xA;   at System.Web.Mvc.MvcHandler.ProcessRequestInit(HttpContextBase httpContext, IController&amp; controller, IControllerFactory&amp; factory)&#xD;&#xA;   at System.Web.Mvc.MvcHandler.BeginProcessRequest(HttpContextBase httpContext, AsyncCallback callback, Object state)&#xD;&#xA;   at System.Web.Mvc.MvcHandler.BeginProcessRequest(HttpContext httpContext, AsyncCallback callback, Object state)&#xD;&#xA;   at System.Web.Mvc.MvcHandler.System.Web.IHttpAsyncHandler.BeginProcessRequest(HttpContext context, AsyncCallback cb, Object extraData)&#xD;&#xA;   at System.Web.HttpApplication.CallHandlerExecutionStep.System.Web.HttpApplication.IExecutionStep.Execute()&#xD;&#xA;   at System.Web.HttpApplication.ExecuteStep(IExecutionStep step, Boolean&amp; completedSynchronously)" time="2016-03-17T11:02:45.6117668Z" statusCode="404">
  <serverVariables>
    <item name="ALL_HTTP">
      <value string="HTTP_CONTENT_TYPE:application/x-www-form-urlencoded&#xD;&#xA;HTTP_ACCEPT:application/json, application/xml, text/json, text/x-json, text/javascript, text/xml&#xD;&#xA;HTTP_ACCEPT_ENCODING:gzip, deflate&#xD;&#xA;HTTP_HOST:localhost:63535&#xD;&#xA;HTTP_USER_AGENT:RestSharp/105.2.3.0&#xD;&#xA;" />
    </item>
    <item name="ALL_RAW">
      <value string="Content-Type: application/x-www-form-urlencoded&#xD;&#xA;Accept: application/json, application/xml, text/json, text/x-json, text/javascript, text/xml&#xD;&#xA;Accept-Encoding: gzip, deflate&#xD;&#xA;Host: localhost:63535&#xD;&#xA;User-Agent: RestSharp/105.2.3.0&#xD;&#xA;" />
    </item>
    <item name="APPL_MD_PATH">
      <value string="/LM/W3SVC/64/ROOT" />
    </item>
    <item name="APPL_PHYSICAL_PATH">
      <value string="D:\CREW\WorkSpace\Development\SourceCode\IPRISM\QR.IPrism\QR.IPrism.Web\" />
    </item>
    <item name="AUTH_TYPE">
      <value string="" />
    </item>
    <item name="AUTH_USER">
      <value string="" />
    </item>
    <item name="AUTH_PASSWORD">
      <value string="*****" />
    </item>
    <item name="LOGON_USER">
      <value string="" />
    </item>
    <item name="REMOTE_USER">
      <value string="" />
    </item>
    <item name="CERT_COOKIE">
      <value string="" />
    </item>
    <item name="CERT_FLAGS">
      <value string="" />
    </item>
    <item name="CERT_ISSUER">
      <value string="" />
    </item>
    <item name="CERT_KEYSIZE">
      <value string="" />
    </item>
    <item name="CERT_SECRETKEYSIZE">
      <value string="" />
    </item>
    <item name="CERT_SERIALNUMBER">
      <value string="" />
    </item>
    <item name="CERT_SERVER_ISSUER">
      <value string="" />
    </item>
    <item name="CERT_SERVER_SUBJECT">
      <value string="" />
    </item>
    <item name="CERT_SUBJECT">
      <value string="" />
    </item>
    <item name="CONTENT_LENGTH">
      <value string="0" />
    </item>
    <item name="CONTENT_TYPE">
      <value string="application/x-www-form-urlencoded" />
    </item>
    <item name="GATEWAY_INTERFACE">
      <value string="CGI/1.1" />
    </item>
    <item name="HTTPS">
      <value string="off" />
    </item>
    <item name="HTTPS_KEYSIZE">
      <value string="" />
    </item>
    <item name="HTTPS_SECRETKEYSIZE">
      <value string="" />
    </item>
    <item name="HTTPS_SERVER_ISSUER">
      <value string="" />
    </item>
    <item name="HTTPS_SERVER_SUBJECT">
      <value string="" />
    </item>
    <item name="INSTANCE_ID">
      <value string="64" />
    </item>
    <item name="INSTANCE_META_PATH">
      <value string="/LM/W3SVC/64" />
    </item>
    <item name="LOCAL_ADDR">
      <value string="::1" />
    </item>
    <item name="PATH_INFO">
      <value string="/Error.cshtml" />
    </item>
    <item name="PATH_TRANSLATED">
      <value string="D:\CREW\WorkSpace\Development\SourceCode\IPRISM\QR.IPrism\QR.IPrism.Web\Error.cshtml" />
    </item>
    <item name="QUERY_STRING">
      <value string="aspxerrorpath=/token" />
    </item>
    <item name="REMOTE_ADDR">
      <value string="::1" />
    </item>
    <item name="REMOTE_HOST">
      <value string="::1" />
    </item>
    <item name="REMOTE_PORT">
      <value string="53776" />
    </item>
    <item name="REQUEST_METHOD">
      <value string="GET" />
    </item>
    <item name="SCRIPT_NAME">
      <value string="/Error.cshtml" />
    </item>
    <item name="SERVER_NAME">
      <value string="localhost" />
    </item>
    <item name="SERVER_PORT">
      <value string="63535" />
    </item>
    <item name="SERVER_PORT_SECURE">
      <value string="0" />
    </item>
    <item name="SERVER_PROTOCOL">
      <value string="HTTP/1.1" />
    </item>
    <item name="SERVER_SOFTWARE">
      <value string="Microsoft-IIS/8.0" />
    </item>
    <item name="URL">
      <value string="/Error.cshtml" />
    </item>
    <item name="HTTP_CONTENT_TYPE">
      <value string="application/x-www-form-urlencoded" />
    </item>
    <item name="HTTP_ACCEPT">
      <value string="application/json, application/xml, text/json, text/x-json, text/javascript, text/xml" />
    </item>
    <item name="HTTP_ACCEPT_ENCODING">
      <value string="gzip, deflate" />
    </item>
    <item name="HTTP_HOST">
      <value string="localhost:63535" />
    </item>
    <item name="HTTP_USER_AGENT">
      <value string="RestSharp/105.2.3.0" />
    </item>
  </serverVariables>
  <queryString>
    <item name="aspxerrorpath">
      <value string="/token" />
    </item>
  </queryString>
  <cookies>
    <item name="ASP.NET_SessionId">
      <value string="mjuidfr35a5wmatmvqdoyqsx" />
    </item>
  </cookies>
</error>